hep_cli/__init__.py
hep_cli/cli.py
hep_cli-0.1.2.dist-info/entry_points.txt
hep_cli-0.1.2.dist-info/LICENSE
hep_cli-0.1.2.dist-info/WHEEL
hep_cli-0.1.2.dist-info/METADATA
hep_cli-0.1.2.dist-info/RECORD
